{
  "query": "distorted reflection",
  "purpose": "single_image",
  "min_width": 256,
  "min_height": 256,
  "last_updated": "2026-04-22T10:48:17.978851+00:00",
  "items": [
    {
      "path": "/mnt/hdd/xuran/multi_image_safety/data/shared_reuse/images/gen/ad7b8d50b933e3c14d26b4aad679cae3ef9f0ab23333dec5a7738d21a918a08d.png",
      "source_type": "gen",
      "provider": "t2i_generated",
      "caption": "distorted reflection",
      "class_label": "distorted reflection",
      "created_by_path": "path1",
      "updated_at": "2026-04-22T10:48:17.978829+00:00"
    }
  ]
}