{
  "query": "hair salon",
  "purpose": "single_image",
  "min_width": 256,
  "min_height": 256,
  "last_updated": "2026-04-24T10:32:32.144615+00:00",
  "items": [
    {
      "path": "/mnt/hdd/xuran/multi_image_safety/data/shared_reuse/images/gen/bd18655a4975408a0ab9664a643ec2bc0afa02d06cc823e536ee7129dc1b6fae.png",
      "source_type": "gen",
      "provider": "t2i_generated",
      "caption": "hair salon",
      "class_label": "hair salon",
      "created_by_path": "path1",
      "updated_at": "2026-04-22T10:43:58.857957+00:00"
    },
    {
      "path": "/mnt2/xuran_hdd/cache/datasets/CC12M_and_Imagenet21K_Recap/images/cc12m/hair_salon/002268553.jpg",
      "source_type": "local",
      "provider": "recap_cc12m",
      "caption": "A modern hair salon with a long row of salon chairs and mirrors, a curved counter with hair products, and a clean, well-lit interior.",
      "class_label": "hair salon",
      "clip_score": 0.2426670491695404,
      "created_by_path": "path6",
      "updated_at": "2026-04-24T10:32:32.144587+00:00"
    }
  ]
}