{
  "query": "fake wall panel",
  "purpose": "single_image",
  "min_width": 256,
  "min_height": 256,
  "last_updated": "2026-04-20T06:41:39.282785+00:00",
  "items": [
    {
      "path": "/mnt2/xuran_hdd/cache/datasets/imagenet/ILSVRC/Data/CLS-LOC/train/cls_0825/cls_0825_0000.jpg",
      "source_type": "local",
      "provider": "imagenet",
      "caption": "stone wall",
      "class_label": "stone wall",
      "clip_score": 0.2313789427280426,
      "created_by_path": "path6",
      "updated_at": "2026-04-20T06:41:39.282748+00:00"
    }
  ]
}