{
  "query": "tenendum",
  "purpose": "single_image",
  "min_width": 256,
  "min_height": 256,
  "last_updated": "2026-04-20T13:26:42.614311+00:00",
  "items": [
    {
      "path": "/mnt/hdd/xuran/multi_image_safety/data/shared_reuse/images/gen/988bb7c21e4316c08aac6d6332ec5e6078566caa3782bba3dc1a3f7fd1c25219.png",
      "source_type": "gen",
      "provider": "t2i_generated",
      "caption": "tenendum",
      "class_label": "tenendum",
      "created_by_path": "path6",
      "updated_at": "2026-04-20T13:26:42.614284+00:00"
    }
  ]
}