{
  "query": "graffiti stencil",
  "purpose": "single_image",
  "min_width": 256,
  "min_height": 256,
  "last_updated": "2026-04-22T11:43:43.306704+00:00",
  "items": [
    {
      "path": "/mnt/hdd/xuran/multi_image_safety/data/shared_reuse/images/gen/f6b518bd1fb440a026fa975d1ddf86ab37a0cd27c3e5e2d403ef1941e371c550.png",
      "source_type": "gen",
      "provider": "t2i_generated",
      "caption": "graffiti stencil",
      "class_label": "graffiti stencil",
      "created_by_path": "path1",
      "updated_at": "2026-04-22T11:43:43.306684+00:00"
    }
  ]
}