{
  "query": "library book return",
  "purpose": "single_image",
  "min_width": 256,
  "min_height": 256,
  "last_updated": "2026-04-20T06:19:03.252623+00:00",
  "items": [
    {
      "path": "/mnt2/xuran_hdd/cache/datasets/open_images/train/corded phone/images/018c5ebe34a9dc05.jpg",
      "source_type": "local",
      "provider": "open_images",
      "caption": "library",
      "class_label": "library",
      "clip_score": 0.22941769659519196,
      "created_by_path": "path6",
      "updated_at": "2026-04-20T06:19:03.252596+00:00"
    }
  ]
}