{
  "query": "locked safe",
  "purpose": "single_image",
  "min_width": 256,
  "min_height": 256,
  "last_updated": "2026-04-22T11:54:57.179169+00:00",
  "items": [
    {
      "path": "/mnt/hdd/xuran/multi_image_safety/data/shared_reuse/images/gen/311a5e7a88e7dec6cd2004e3aa384bfd8ad1c3b23f43fc731eea18bf75f50947.png",
      "source_type": "gen",
      "provider": "t2i_generated",
      "caption": "locked safe deposit box",
      "class_label": "locked safe",
      "created_by_path": "path1",
      "updated_at": "2026-04-22T11:54:57.179150+00:00"
    }
  ]
}