{
  "query": "generic perfume bottle",
  "purpose": "single_image",
  "min_width": 256,
  "min_height": 256,
  "last_updated": "2026-04-24T10:43:07.146899+00:00",
  "items": [
    {
      "path": "/mnt/hdd/xuran/multi_image_safety/data/shared_reuse/images/web/1dd70aba4d70136f0dd4aa6be2725b19ebba4dcf841905ef1a21b3cf3bba1296.png",
      "source_type": "web",
      "provider": "wikimedia_commons",
      "caption": "L'Heure Bleue",
      "class_label": "",
      "clip_score": 0.2780907154083252,
      "url": "https://upload.wikimedia.org/wikipedia/commons/a/a9/L%27Heure_Bleue.jpg",
      "created_by_path": "path6",
      "updated_at": "2026-04-24T10:43:07.146852+00:00"
    }
  ]
}