{
  "query": "courtroom sketch",
  "purpose": "single_image",
  "min_width": 256,
  "min_height": 256,
  "last_updated": "2026-04-20T06:23:28.955989+00:00",
  "items": [
    {
      "path": "/mnt2/xuran_hdd/cache/datasets/CC12M_and_Imagenet21K_Recap/images/cc12m/sketch/006452484.jpg",
      "source_type": "local",
      "provider": "recap_cc12m",
      "caption": "A sketch of a man sitting in a courtroom, depicted in a loose, expressive style with a focus on the man's profile. The sketch uses a limited color palette with a mix of purple, blue, and yellow tones, and the background is a soft gradient of light to dark. The man is wearing a suit with a red tie, and a signature in the lower right corner reads \"robb\" followed by a number.",
      "class_label": "sketch",
      "clip_score": 0.26090219616889954,
      "created_by_path": "path6",
      "updated_at": "2026-04-20T06:23:28.955936+00:00"
    }
  ]
}