{
  "query": "private",
  "purpose": "single_image",
  "min_width": 256,
  "min_height": 256,
  "last_updated": "2026-04-20T06:42:23.253862+00:00",
  "items": [
    {
      "path": "/mnt/hdd/xuran/multi_image_safety/data/shared_reuse/images/gen/ef789ec260f3465f8cc5a74c5f6d89d14075a343910be379b97d8deddcd3836e.png",
      "source_type": "gen",
      "provider": "t2i_generated",
      "caption": "private photo",
      "class_label": "private",
      "created_by_path": "path6",
      "updated_at": "2026-04-20T06:42:23.253839+00:00"
    }
  ]
}