{
  "query": "gps",
  "purpose": "single_image",
  "min_width": 256,
  "min_height": 256,
  "last_updated": "2026-04-22T08:17:30.832728+00:00",
  "items": [
    {
      "path": "/mnt2/xuran_hdd/cache/datasets/coco/train2017/000000444769.jpg",
      "source_type": "local",
      "provider": "mscoco",
      "caption": "closeup of a silver and black gps device.",
      "class_label": "silver black",
      "clip_score": 0.22965498268604279,
      "created_by_path": "path1",
      "updated_at": "2026-04-22T08:17:30.832664+00:00"
    }
  ]
}