{
  "query": "wooden sign",
  "purpose": "single_image",
  "min_width": 256,
  "min_height": 256,
  "last_updated": "2026-04-20T06:29:49.660897+00:00",
  "items": [
    {
      "path": "/mnt/hdd/xuran/multi_image_safety/data/shared_reuse/images/gen/1fd19dbfd4f509a5efab725395e426c9e16283628af50caa7fa5c5760c422e3c.png",
      "source_type": "gen",
      "provider": "t2i_generated",
      "caption": "wooden sign",
      "class_label": "wooden sign",
      "created_by_path": "path6",
      "updated_at": "2026-04-20T06:29:49.660871+00:00"
    }
  ]
}