{
  "query": "corporate server",
  "purpose": "single_image",
  "min_width": 256,
  "min_height": 256,
  "last_updated": "2026-04-20T06:09:56.267333+00:00",
  "items": [
    {
      "path": "/mnt2/xuran_hdd/cache/datasets/CC12M_and_Imagenet21K_Recap/images/cc12m/humanoid_figures/005828945.jpg",
      "source_type": "local",
      "provider": "recap_cc12m",
      "caption": "A 3d rendering featuring three humanoid figures, each holding a server rack. the figure on the left is holding a server rack with a black casing and blue lights, the central figure is holding a server rack with a black casing and white lights, and the figure on the right is holding a server rack with a black casing and blue lights. the server racks are standing upright and appear to be of a similar design, with multiple shelves and compartments. the background is plain white, emphasizing the subjects. the style of the image is clean and professional, likely intended for use in a corporate or technical context.",
      "class_label": "humanoid figures",
      "clip_score": 0.23723118007183075,
      "created_by_path": "path6",
      "updated_at": "2026-04-20T06:09:56.267288+00:00"
    }
  ]
}